{
  "$schema": "https://mintlify.com/docs.json",
  "theme": "maple",
  "name": "PZLR",
  "colors": {
    "primary": "#16A34A",
    "light": "#07C983",
    "dark": "#15803D"
  },
  "favicon": "/favicon.svg",
  "navigation": {
    "groups": [
      {
        "group": "Agents",
        "pages": [
          {
            "group": "RAG-Agent",
            "pages": ["pages/rag-agent/indexierung", "pages/indexer/test"]
          },
          "pages/sales-agent/comingsoon",
          "pages/recruiting-agent/comingsoon"
        ]
      },
      {
        "group": "Dashboard",
        "pages": [
          "pages/dashboard/urls",
          "pages/dashboard/dateien",
          "pages/dashboard/chatsessions"
          ]
      }
    ],
    "global": {
      "anchors": [
        {
          "anchor": "Agent-Demo",
          "href": "https://mintlify.com/docs",
          "icon": "book-open-cover"
        },
        {
          "anchor": "Community",
          "href": "https://mintlify.com/community",
          "icon": "slack"
        },
        {
          "anchor": "Blog",
          "href": "https://mintlify.com/blog",
          "icon": "newspaper"
        }
      ]
    }
  },
  "logo": {
    "light": "/logo/light.svg",
    "dark": "/logo/dark.svg"
  },
  "navbar": {
    "links": [
      {
        "label": "Support",
        "href": "mailto:support@pzlr.ai"
      }
    ],
    "primary": {
      "type": "button",
      "label": "Website",
      "href": "https://pzlr.ai"
    }
  },
  "footer": {
    "socials": {
      "linkedin": "https://linkedin.com/company/mintlify"
    }
  }
}